scattering_compositional_learner/__init__.py
scattering_compositional_learner/scl.py
scattering_compositional_learner-0.1.0.dist-info/LICENSE
scattering_compositional_learner-0.1.0.dist-info/METADATA
scattering_compositional_learner-0.1.0.dist-info/WHEEL
scattering_compositional_learner-0.1.0.dist-info/top_level.txt
scattering_compositional_learner-0.1.0.dist-info/RECORD
