Metadata-Version: 2.1
Name: scattering-compositional-learner
Version: 0.1.0
Summary: Scattering Compositional Learner for solving Raven's Progressive Matrices
Home-page: https://github.com/mikomel/scattering-compositional-learner
Author: Mikołaj Małkiński
Author-email: mikolaj.malkinski@gmail.com
License: MIT
Keywords: artificial intelligence,scattering compositional learner
Platform: UNKNOWN
Classifier: Development Status :: 4 - Beta
Classifier: Intended Audience :: Developers
Classifier: License :: OSI Approved :: MIT License
Classifier: Operating System :: OS Independent
Classifier: Programming Language :: Python :: 3.6
Classifier: Topic :: Scientific/Engineering :: Artificial Intelligence
Requires-Python: >=3.6
Requires-Dist: torch (>=1.5)
